[
  {
    "id": "Guest",
    "team":"Adelaide Spurs",
    "name":"Mohannad Alotaibi",
    "shirtno":""
  },
  {
    "id": "Guest",
    "team":"Adelaide Spurs",
    "name":"Ciro Jimenez",
    "shirtno":""
  },
  {
    "id": "Guest",
    "team":"Adelaide Spurs",
    "name":"Philip Richards",
    "shirtno":""
  },
  {
    "id": "Guest",
    "team":"Monarchs",
    "name":"Yong Chin",
    "shirtno":""
  },
  {
    "id": "Guest",
    "team":"Monarchs",
    "name":"Ron Van Ayswyk",
    "shirtno":""
  },
  {
    "id": "Guest",
    "team":"West Beach Old Boys",
    "name":"Andy Firth",
    "shirtno":""
  },
  {
    "id": "Guest",
    "team":"West Beach Old Boys",
    "name":"Bill Houston",
    "shirtno":""
  },
  {
    "id": "Guest",
    "team":"West Beach Old Boys",
    "name":"Mason Willis",
    "shirtno":""
  },
  {
    "id": "Guest",
    "team":"West Beach Old Boys",
    "name":"Damien Hassell",
    "shirtno":""
  },
  {
    "id": "Guest",
    "team":"West Beach Old Boys",
    "name":"Peter Drapaniutis",
    "shirtno":""
  },
  {
    "id": "Guest",
    "team":"West Beach Old Boys",
    "name":"Tom Lowe",
    "shirtno":""
  },
  {
    "id": "Guest",
    "team":"West Beach Old Boys",
    "name":"John Raschella",
    "shirtno":""
  },
  {
    "id": "Guest",
    "team":"West Beach Old Boys",
    "name":"David Robison",
    "shirtno":""
  },
  {
    "id": "Guest",
    "team":"Sturt-Marion B",
    "name":"Chris Nugent",
    "shirtno":""
  },
  {
    "id": "Guest",
    "team":"Sturt-Marion B",
    "name":"Arthus Paragalas",
    "shirtno":""
  },
  {
    "id": "Guest",
    "team":"Sturt-Marion B",
    "name":"Tom Williams",
    "shirtno":""
  },
  {
    "id": "Guest",
    "team":"Sturt-Marion",
    "name":"Joseph Campbell",
    "shirtno":""
  },
  {
    "id": "Guest",
    "team":"Sturt-Marion",
    "name":"Andrew McAuley",
    "shirtno":""
  },
  {
    "id": "Guest",
    "team":"Sturt-Marion",
    "name":"Mustapha Hussein",
    "shirtno":""
  },
  {
    "id": "Guest",
    "team":"West Beach",
    "name":"Torsten Rutter",
    "shirtno":""
  },
  {
    "id": "Guest",
    "team":"West Beach",
    "name":"Ben Yelland",
    "shirtno":""
  },
  {
    "id": "Guest",
    "team":"West Beach",
    "name":"Steve Fulton",
    "shirtno":""
  },
  {
    "id": "Guest",
    "team":"West Beach",
    "name":"Scot Bradley",
    "shirtno":""
  },
  {
    "id": "Guest",
    "team":"Phoenix",
    "name":"Mauigok Ajai Wai",
    "shirtno":""
  },
  {
    "id": "Guest",
    "team":"Phoenix",
    "name":"Adrian Mhillaj",
    "shirtno":""
  },
  {
    "id": "Guest",
    "team":"Old Plymptonians",
    "name":"Ricky Pickles",
    "shirtno":""
  },
  {
    "id": "Guest",
    "team":"Old Plymptonians",
    "name":"Kev Lyne",
    "shirtno":""
  },
  {
    "id": "Guest",
    "team":"Old Plymptonians",
    "name":"Dave Southwell",
    "shirtno":""
  },
  {
    "id": "Guest",
    "team":"Austria",
    "name":"Steve Gawthrop",
    "shirtno":""
  },
  {
    "id": "Guest",
    "team":"Austria",
    "name":"Michael Rock",
    "shirtno":""
  },
  {
    "id": "Guest",
    "team":"Croatia",
    "name":"Souk Douauotony",
    "shirtno":""
  },
  {
    "id": "Guest",
    "team":"Man City",
    "name":"Wayne Heald",
    "shirtno":""
  },
  {
    "id": "Guest",
    "team":"Man City",
    "name":"Rob Arnold",
    "shirtno":""
  },
  {
    "id": "Guest",
    "team":"Man City",
    "name":"Richard Graham",
    "shirtno":""
  },
  {
    "id": "Guest",
    "team":"University Orange",
    "name":"Dan Kerber",
    "shirtno":""
  },
  {
    "id": "Guest",
    "team":"University Orange",
    "name":"Jon Walsh",
    "shirtno":""
  },
  {
    "id": "Guest",
    "team":"Pulteney",
    "name":"Cristian Douglas",
    "shirtno":""
  },
  {
    "id": "Guest",
    "team":"Southern Cross",
    "name":"Daniel Howlett",
    "shirtno":""
  },
  {
    "id": "Guest",
    "team":"Southern Cross",
    "name":"Simon Darwood",
    "shirtno":""
  }
]